duco.ducobox-0.3.1-nspkg.pth
duco/__ducobox_version__.py
duco/__version__.py
duco/ducobox.py
duco.ducobox-0.3.1.dist-info/DESCRIPTION.rst
duco.ducobox-0.3.1.dist-info/METADATA
duco.ducobox-0.3.1.dist-info/RECORD
duco.ducobox-0.3.1.dist-info/WHEEL
duco.ducobox-0.3.1.dist-info/entry_points.txt
duco.ducobox-0.3.1.dist-info/metadata.json
duco.ducobox-0.3.1.dist-info/namespace_packages.txt
duco.ducobox-0.3.1.dist-info/top_level.txt
