Metadata-Version: 2.0
Name: duco.ducobox
Version: 0.3.1
Summary: Read parameters from DucoBox.
Home-page: https://github.com/SteinHeselmans/DucoBox
Author: Stein Heselmans
Author-email: stein.heselmans@gmail.com
License: GNU General Public License v3 (GPLv3)
Keywords: Duco,DucoBox,DucoBox Silent,ventilation,home automation
Platform: any
Classifier: Development Status :: 1 - Planning
Classifier: Intended Audience :: End Users/Desktop
Classifier: License :: OSI Approved :: GNU General Public License v3 (GPLv3)
Classifier: Operating System :: Unix
Classifier: Operating System :: POSIX
Classifier: Operating System :: Microsoft :: Windows
Classifier: Programming Language :: Python
Classifier: Programming Language :: Python :: 2.7
Classifier: Programming Language :: Python :: 3
Classifier: Programming Language :: Python :: 3.3
Classifier: Programming Language :: Python :: 3.4
Classifier: Programming Language :: Python :: 3.5
Classifier: Programming Language :: Python :: 3.6
Classifier: Programming Language :: Python :: 3.7
Classifier: Topic :: Home Automation
Requires-Dist: influxdb
Requires-Dist: pyserial
Requires-Dist: setuptools-scm
